{
  "quotationNumber": "20269993",
  "documentId": "784d07be-5c25-4366-a4e4-9b445dc25aa3",
  "name": "Kelly Verheijen",
  "timestamp": "2026-07-18T11:00:54.151Z",
  "lines": [
    {
      "units": 1,
      "description": "Rolluik (RollSUPER)\nBreedte: 1700 mm\nHoogte: 1700 mm\nKastmaat: 170 mm (schuin)\nFrame Kleur: RAL 7016 structuur\nKleur Pantser: RAL 7016\nOnderlat: Standaard\nBediening: Somfy IO motor solar\nPaneel zijde: NTB\nLamel: RS 42, 1,0 cm dik.\nMontage: NTB\n\nGarantie:\n- 5 jaar op het product\n- 7 jaar op de motor",
      "pricePerUnit": 1354.6,
      "vatPercentage": 21,
      "lockTotalPrice": false
    },
    {
      "units": 1,
      "description": "Inmeten + montage rolluik solar\n- Montage\n- Klein materiaal\n- Afstellen motor\n- Verwerken verpakkingsmateriaal",
      "pricePerUnit": 175,
      "vatPercentage": 21,
      "lockTotalPrice": false
    }
  ]
}