{
  "quotationNumber": "20268929",
  "documentId": "88567451-d576-444c-b762-e95071dc1fb2",
  "name": "Cor Molenaar",
  "timestamp": "2026-07-07T12:30:47.597Z",
  "lines": [
    {
      "units": 1,
      "description": "Zip Design 110\nBreedte: 600 mm\nHoogte: 1000 mm\nKastmaat: 105 mm\nFrame kleur: RAL 9001\nKleur doek: NTB\nOnderlat: Design\nBediening: Draaischakelaar\nMontage: NTB\nType geleider: NTB\n\nGarantie:\n- 5 jaar op het product\n- 7 jaar op de motor",
      "pricePerUnit": 974.7,
      "vatPercentage": 21,
      "lockTotalPrice": false
    },
    {
      "units": 1,
      "description": "Inmeten + montage screen solar\n- Montage\n- Klein materiaal\n- Afstellen motor\n- Verwerken verpakkingsmateriaal",
      "pricePerUnit": 175,
      "vatPercentage": 21,
      "lockTotalPrice": false
    },
    {
      "units": 1,
      "description": "Zip Design 110\nBreedte: 2829 mm\nHoogte: 1752 mm\nKastmaat: 105 mm\nFrame kleur: RAL 9001\nKleur doek: NTB\nOnderlat: Design\nBediening: Draaischakelaar\nMontage: NTB\nType geleider: NTB\n\nGarantie:\n- 5 jaar op het product\n- 7 jaar op de motor",
      "pricePerUnit": 1744.7,
      "vatPercentage": 21,
      "lockTotalPrice": false
    },
    {
      "units": 1,
      "description": "Inmeten + montage screen solar\n- Montage\n- Klein materiaal\n- Afstellen motor\n- Verwerken verpakkingsmateriaal",
      "pricePerUnit": 175,
      "vatPercentage": 21,
      "lockTotalPrice": false
    }
  ]
}