{
  "quotationNumber": "202626963",
  "documentId": "a82fb682-6c0e-476d-8315-2a4d7f77a010",
  "name": "J. Thijssen",
  "timestamp": "2026-07-02T11:01:10.103Z",
  "lines": [
    {
      "units": 1,
      "description": "SunElite\nBreedte: 6000 mm\nUitval: 3000 mm\nFrame Kleur: RAL 7016 structuur\nKleur doek: NTB\nBediening: Draaischakelaar\nMotorzijde: NTB\nKleur/lengte motorkabel: NTB\nOverige: NTB\n\nGarantie:\n- 5 jaar op het product.\n- 7 jaar op de motor",
      "pricePerUnit": 4930.9,
      "vatPercentage": 21,
      "lockTotalPrice": false
    },
    {
      "units": 1,
      "description": "Inmeten + montage Knikarmscherm.\n- Zonder uitbouw\n- Montage d.m.v. chemisch anker\n- Afwerken elektra\n- Klein materiaal\n- Afstellen zonwering\n- Verwerken verpakkingsmateriaal",
      "pricePerUnit": 275,
      "vatPercentage": 21,
      "lockTotalPrice": false
    },
    {
      "units": 1,
      "description": "Eolis 3D windsensor IO\n- Windbeveiliging in de voorlijst\n- De windsensor is een hulp stuk hier kunnen geen garantie rechten aan verleend worden mbt windschade.",
      "pricePerUnit": 169,
      "vatPercentage": 21,
      "lockTotalPrice": false
    }
  ]
}