{
  "quotationNumber": "20266948",
  "documentId": "56f09ccf-9b58-4f4b-accc-8c00f937cec7",
  "name": "Ben Hooijberg",
  "timestamp": "2026-06-12T19:43:31.745Z",
  "lines": [
    {
      "units": 1,
      "description": "Zip Design 110\nBreedte: 3190 mm\nHoogte: 1550 mm\nKastmaat: 105 mm\nFrame kleur: RAL 7016 structuur\nKleur doek: NTB\nOnderlat: Design\nBediening: Draaischakelaar\nMontage: NTB\nType geleider: NTB\n\nGarantie:\n- 5 jaar op het product\n- 7 jaar op de motor",
      "pricePerUnit": 1720.5,
      "imageUri": null,
      "vatPercentage": 21,
      "discount": null,
      "position": null,
      "lockTotalPrice": false
    },
    {
      "units": 1,
      "description": "Inmeten + montage screen solar\n- Montage\n- Klein materiaal\n- Afstellen motor\n- Verwerken verpakkingsmateriaal",
      "pricePerUnit": 175,
      "imageUri": null,
      "vatPercentage": 21,
      "discount": null,
      "position": null,
      "lockTotalPrice": false
    }
  ]
}