{
  "quotationNumber": "20269723",
  "documentId": "0e347787-f905-4001-b588-573567c88c6d",
  "name": "Micky Van Wingerden",
  "timestamp": "2026-07-15T07:30:54.950Z",
  "lines": [
    {
      "units": 1,
      "description": "Rolluik (RollSUPER)\nBreedte: 2000 mm\nHoogte: 1200 mm\nKastmaat: 170 mm (schuin)\nFrame Kleur: RAL 7016 structuur\nKleur Pantser: RAL 7016\nOnderlat: Standaard\nBediening: Draaischakelaar\nPaneel zijde: NTB\nLamel: RS 42, 1,0 cm dik.\nMontage: NTB\n\nGarantie:\n- 5 jaar op het product\n- 7 jaar op de motor",
      "pricePerUnit": 849.3,
      "vatPercentage": 21,
      "lockTotalPrice": false
    },
    {
      "units": 1,
      "description": "Inmeten + montage rolluik solar\n- Montage\n- Klein materiaal\n- Afstellen motor\n- Verwerken verpakkingsmateriaal",
      "pricePerUnit": 175,
      "vatPercentage": 21,
      "lockTotalPrice": false
    }
  ]
}