{
  "documentId": "2f2684cd-bf9d-4fbd-9d29-748645ec138d",
  "versionId": "3a4f884b-d753-4c69-9c4a-b9aa6a4f63d5",
  "profileId": null,
  "documentTitle": "Offerte #20268284",
  "documentStatus": "DRAFT",
  "documentNumber": "20268284",
  "documentType": "QUOTATION",
  "title": "Offerte #20268284",
  "quotationNumber": "20268284",
  "quotationTitle": "Offerte #20268284",
  "quotationCreationTimestamp": 1782803826948,
  "quotationExpirationTimestamp": 1785395826948,
  "quotationStatus": "DRAFT",
  "isoCurrency": "EUR",
  "locale": "nl-NL",
  "subjects": {
    "leadConfiguration": "0bda7fec-83f9-4197-8898-394391677b42",
    "contactPerson": "5bb5ac50-3488-4212-b706-06ab4c5babe3"
  },
  "segments": {
    "defaultTemplateContactPart": {
      "type": "contactPerson",
      "data": "**${organisation.name}**\n${organisation.address}\n**${contactPerson.name}**\n${contactPerson.address}\n${contactPerson.email}\n${contactPerson.phoneNumber}"
    },
    "defaultUserDeclinePart": {
      "type": "userDecline",
      "data": {
        "isDeclinedByCustomer": null,
        "signingProps": null,
        "artifactName": null,
        "timestamp": null
      }
    },
    "defaultSignaturePart": {
      "type": "signature",
      "data": {
        "isSignedByCustomer": null,
        "signingProps": null,
        "artifactName": null,
        "timestamp": null
      }
    },
    "defaultTemplateProfileLogo": {
      "type": "companyProfileLogo",
      "data": "![|6lh]($companyProfile.logo)"
    },
    "defaultTemplateProfileText": {
      "type": "text",
      "data": "[[right]]**${companyProfile.name}**\n${companyProfile.addressLine}\n${companyProfile.postalCode} ${companyProfile.city}"
    },
    "defaultTemplatePriceLineGroup": {
      "type": "priceLineGroup",
      "data": {
        "name": null,
        "lines": [
          {
            "units": 1,
            "description": "",
            "pricePerUnit": null,
            "imageUri": null,
            "vatPercentage": 21,
            "discount": null,
            "position": null,
            "lockTotalPrice": false
          }
        ],
        "vatSetting": "INCL",
        "groupDiscount": null,
        "showPrices": null
      }
    }
  },
  "pricing": {
    "total": 0
  },
  "renderRows": [
    {
      "delegateMargins": false,
      "widths": [
        50,
        50
      ],
      "columns": [
        {
          "elements": [
            {
              "type": "text",
              "target": "defaultTemplateProfileLogo"
            }
          ]
        },
        {
          "elements": [
            {
              "type": "text",
              "target": "defaultTemplateProfileText"
            }
          ]
        }
      ]
    },
    {
      "delegateMargins": false,
      "widths": [
        100
      ],
      "columns": [
        {
          "elements": [
            {
              "type": "empty",
              "target": null
            }
          ]
        }
      ]
    },
    {
      "delegateMargins": false,
      "widths": [
        100
      ],
      "columns": [
        {
          "elements": [
            {
              "type": "text",
              "target": "defaultTemplateContactPart"
            }
          ]
        }
      ]
    },
    {
      "delegateMargins": false,
      "widths": [
        100
      ],
      "columns": [
        {
          "elements": [
            {
              "type": "empty",
              "target": "2lh"
            }
          ]
        }
      ]
    },
    {
      "delegateMargins": false,
      "widths": [
        100
      ],
      "columns": [
        {
          "elements": [
            {
              "type": "quotationData",
              "target": null
            }
          ]
        }
      ]
    },
    {
      "delegateMargins": false,
      "widths": [
        100
      ],
      "columns": [
        {
          "elements": [
            {
              "type": "empty",
              "target": "2lh"
            }
          ]
        }
      ]
    },
    {
      "delegateMargins": false,
      "widths": [
        100
      ],
      "columns": [
        {
          "elements": [
            {
              "type": "priceLineGroupCombined",
              "target": "defaultTemplatePriceLineGroup"
            }
          ]
        }
      ]
    },
    {
      "delegateMargins": false,
      "widths": [
        100
      ],
      "columns": [
        {
          "elements": [
            {
              "type": "empty",
              "target": "2lh"
            }
          ]
        }
      ]
    },
    {
      "delegateMargins": false,
      "widths": [
        50,
        50
      ],
      "columns": [
        {
          "elements": [
            {
              "type": "userDecline",
              "target": "defaultUserDeclinePart"
            }
          ]
        },
        {
          "elements": [
            {
              "type": "signature",
              "target": "defaultSignaturePart"
            }
          ]
        }
      ]
    }
  ],
  "renderTemplate": null,
  "artifacts": null
}