{
  "quotationNumber": "20267056",
  "documentId": "1a2047b5-2ba4-44da-9831-40bd840201c9",
  "name": "Jeffrey Onstein",
  "timestamp": "2026-06-15T07:30:45.400Z",
  "lines": [
    {
      "units": 2,
      "description": "Rolluik (RollSUPER)\nBreedte: 2200 mm\nHoogte: 1550 mm\nKastmaat: 170 mm (schuin)\nFrame Kleur: RAL 9010\nKleur Pantser: RAL 7016\nOnderlat: Standaard\nBediening: Draaischakelaar\nPaneel zijde: NTB\nLamel: RS 42, 1,0 cm dik.\nMontage: NTB\n\nGarantie:\n- 5 jaar op het product\n- 7 jaar op de motor",
      "pricePerUnit": 978,
      "imageUri": null,
      "vatPercentage": 21,
      "discount": null,
      "position": null,
      "lockTotalPrice": false
    },
    {
      "units": 2,
      "description": "Inmeten + montage rolluik solar\n- Montage\n- Klein materiaal\n- Afstellen motor\n- Verwerken verpakkingsmateriaal",
      "pricePerUnit": 175,
      "imageUri": null,
      "vatPercentage": 21,
      "discount": null,
      "position": null,
      "lockTotalPrice": false
    },
    {
      "units": 1,
      "description": "Rolluik (RollSUPER)\nBreedte: 1000 mm\nHoogte: 1100 mm\nKastmaat: 170 mm (schuin)\nFrame Kleur: RAL 9010\nKleur Pantser: RAL 7016\nOnderlat: Standaard\nBediening: Draaischakelaar\nPaneel zijde: NTB\nLamel: RS 42, 1,0 cm dik.\nMontage: NTB\n\nGarantie:\n- 5 jaar op het product\n- 7 jaar op de motor",
      "pricePerUnit": 646.9,
      "imageUri": null,
      "vatPercentage": 21,
      "discount": null,
      "position": null,
      "lockTotalPrice": false
    },
    {
      "units": 1,
      "description": "Inmeten + montage rolluik solar\n- Montage\n- Klein materiaal\n- Afstellen motor\n- Verwerken verpakkingsmateriaal",
      "pricePerUnit": 175,
      "imageUri": null,
      "vatPercentage": 21,
      "discount": null,
      "position": null,
      "lockTotalPrice": false
    },
    {
      "units": 1,
      "description": "Rolluik (RollSUPER)\nBreedte: 1550 mm\nHoogte: 2050 mm\nKastmaat: 170 mm (schuin)\nFrame Kleur: RAL 9010\nKleur Pantser: RAL 7016\nOnderlat: Standaard\nBediening: Draaischakelaar\nPaneel zijde: NTB\nLamel: RS 42, 1,0 cm dik.\nMontage: NTB\n\nGarantie:\n- 5 jaar op het product\n- 7 jaar op de motor",
      "pricePerUnit": 986.8,
      "imageUri": null,
      "vatPercentage": 21,
      "discount": null,
      "position": null,
      "lockTotalPrice": false
    },
    {
      "units": 1,
      "description": "Inmeten + montage rolluik solar\n- Montage\n- Klein materiaal\n- Afstellen motor\n- Verwerken verpakkingsmateriaal",
      "pricePerUnit": 175,
      "imageUri": null,
      "vatPercentage": 21,
      "discount": null,
      "position": null,
      "lockTotalPrice": false
    }
  ]
}