{
  "quotationNumber": "20267754",
  "documentId": "a28076d0-7143-4789-8f7c-ea1d009b23f6",
  "name": "Janine  McCaughey",
  "timestamp": "2026-06-25T07:31:53.911Z",
  "lines": [
    {
      "units": 1,
      "description": "Zip Design 110\nBreedte: 2050 mm\nHoogte: 1000 mm\nKastmaat: 105 mm\nFrame kleur: RAL 9010\nKleur doek: NTB\nOnderlat: Design\nBediening: Motor + afstandsbediening\nMontage: NTB\nType geleider: NTB\n\nGarantie:\n- 5 jaar op het product\n- 7 jaar op de motor",
      "pricePerUnit": 1734.1,
      "imageUri": null,
      "vatPercentage": 21,
      "discount": null,
      "position": null,
      "lockTotalPrice": false
    },
    {
      "units": 1,
      "description": "Inmeten + montage screen solar\n- Montage\n- Klein materiaal\n- Afstellen motor\n- Verwerken verpakkingsmateriaal",
      "pricePerUnit": 175,
      "imageUri": null,
      "vatPercentage": 21,
      "discount": null,
      "position": null,
      "lockTotalPrice": false
    },
    {
      "units": 1,
      "description": "Rolluik (RollSUPER)\nBreedte: 3810 mm\nHoogte: 1173 mm\nKastmaat: 170 mm (schuin)\nFrame Kleur: RAL 9010\nKleur Pantser: RAL 7016\nOnderlat: Standaard\nBediening: Draaischakelaar\nPaneel zijde: NTB\nLamel: RS 42, 1,0 cm dik.\nMontage: NTB\n\nGarantie:\n- 5 jaar op het product\n- 7 jaar op de motor",
      "pricePerUnit": 1247.5,
      "imageUri": null,
      "vatPercentage": 21,
      "discount": null,
      "position": null,
      "lockTotalPrice": false
    },
    {
      "units": 1,
      "description": "Zip Design 110\nBreedte: 2400 mm\nHoogte: 1000 mm\nKastmaat: 105 mm\nFrame kleur: RAL 9010\nKleur doek: NTB\nOnderlat: Design\nBediening: Motor + afstandsbediening\nMontage: NTB\nType geleider: NTB\n\nGarantie:\n- 5 jaar op het product\n- 7 jaar op de motor",
      "pricePerUnit": 1774.8,
      "imageUri": null,
      "vatPercentage": 21,
      "discount": null,
      "position": null,
      "lockTotalPrice": false
    },
    {
      "units": 1,
      "description": "Inmeten + montage screen solar\n- Montage\n- Klein materiaal\n- Afstellen motor\n- Verwerken verpakkingsmateriaal",
      "pricePerUnit": 175,
      "imageUri": null,
      "vatPercentage": 21,
      "discount": null,
      "position": null,
      "lockTotalPrice": false
    }
  ]
}