{
 "documentId": "a82be8d9-4bd1-4b5a-a408-7c292445af46",
 "versionId": "2826acdb-c6bd-4f1f-96d4-c90b73120bf5",
 "documentTitle": "Offerte #20266816",
 "documentStatus": "SENT",
 "documentNumber": "20266816",
 "documentType": "QUOTATION",
 "title": "Offerte #20266816",
 "quotationNumber": "20266816",
 "quotationTitle": "Offerte #20266816",
 "quotationCreationTimestamp": 1780918145068,
 "quotationExpirationTimestamp": 1783510145068,
 "quotationStatus": "SENT",
 "isoCurrency": "EUR",
 "subjects": {
  "leadConfiguration": "cdd5ed7f-34e3-4d55-bec9-f2296a94827b",
  "contactPerson": "6e51c5ec-b46a-49c8-b1c7-d1bdec42f8d7"
 },
 "segments": {
  "defaultTemplateContactPart": {
   "type": "contactPerson",
   "data": "**${contactPerson.name}**\n${contactPerson.address}\n${contactPerson.email}\n${contactPerson.phoneNumber}"
  },
  "defaultSignaturePart": {
   "type": "signature",
   "data": {}
  },
  "defaultTemplateProfileLogo": {
   "type": "companyProfileLogo",
   "data": "![|6lh]($companyProfile.logo)"
  },
  "defaultTemplateProfileText": {
   "type": "text",
   "data": "[[right]]**${companyProfile.name}**\n${companyProfile.addressLine}\n${companyProfile.postalCode} ${companyProfile.city}"
  },
  "defaultTemplatePriceLineGroup": {
   "type": "priceLineGroup",
   "data": {
    "lines": [
     {
      "units": 1,
      "description": "Suneye\nBreedte: 4400 mm\nUitval: 3000 mm\nFrame kleur: RAL 7016 structuur\nKleur doek: NTB\nBediening: Motor + afstandsbediening\nMotorzijde: NTB\nKleur/lengte motorkabel: NTB\nOverige: NTB\n\nGarantie:\n- 5 jaar op het product\n- 7 jaar op de motor",
      "pricePerUnit": 3338,
      "vatPercentage": 21,
      "position": 0,
      "lockTotalPrice": false
     },
     {
      "units": 1,
      "description": "Inmeten + montage Knikarmscherm.\n- Zonder uitbouw\n- Montage d.m.v. chemisch anker\n- Afwerken elektra\n- Klein materiaal\n- Afstellen zonwering\n- Verwerken verpakkingsmateriaal",
      "pricePerUnit": 250,
      "vatPercentage": 21,
      "position": 1,
      "lockTotalPrice": false
     }
    ],
    "vatSetting": "INCL",
    "groupDiscount": {
     "name": "15% tijdelijke actie",
     "amount": 15,
     "type": "PERCENTAGE",
     "vatPercentage": 21
    }
   }
  }
 },
 "pricing": {
  "total": 3049.8
 },
 "renderRows": [
  {
   "delegateMargins": false,
   "widths": [
    50,
    50
   ],
   "columns": [
    {
     "elements": [
      {
       "type": "text",
       "target": "defaultTemplateProfileLogo"
      }
     ]
    },
    {
     "elements": [
      {
       "type": "text",
       "target": "defaultTemplateProfileText"
      }
     ]
    }
   ]
  },
  {
   "delegateMargins": false,
   "widths": [
    100
   ],
   "columns": [
    {
     "elements": [
      {
       "type": "empty"
      }
     ]
    }
   ]
  },
  {
   "delegateMargins": false,
   "widths": [
    100
   ],
   "columns": [
    {
     "elements": [
      {
       "type": "text",
       "target": "defaultTemplateContactPart"
      }
     ]
    }
   ]
  },
  {
   "delegateMargins": false,
   "widths": [
    100
   ],
   "columns": [
    {
     "elements": [
      {
       "type": "empty",
       "target": "2lh"
      }
     ]
    }
   ]
  },
  {
   "delegateMargins": false,
   "widths": [
    100
   ],
   "columns": [
    {
     "elements": [
      {
       "type": "quotationData"
      }
     ]
    }
   ]
  },
  {
   "delegateMargins": false,
   "widths": [
    100
   ],
   "columns": [
    {
     "elements": [
      {
       "type": "empty",
       "target": "2lh"
      }
     ]
    }
   ]
  },
  {
   "delegateMargins": false,
   "widths": [
    100
   ],
   "columns": [
    {
     "elements": [
      {
       "type": "priceLineGroupCombined",
       "target": "defaultTemplatePriceLineGroup"
      }
     ]
    }
   ]
  },
  {
   "delegateMargins": false,
   "widths": [
    100
   ],
   "columns": [
    {
     "elements": [
      {
       "type": "empty",
       "target": "2lh"
      }
     ]
    }
   ]
  },
  {
   "delegateMargins": false,
   "widths": [
    50,
    50
   ],
   "columns": [
    {
     "elements": [
      {
       "type": "userDecline"
      }
     ]
    },
    {
     "elements": [
      {
       "type": "signature",
       "target": "defaultSignaturePart"
      }
     ]
    }
   ]
  }
 ]
}