{
 "documentId": "b16b4a1f-3843-4800-835a-7f54adfac2e2",
 "versionId": "555bab8b-d31c-4b13-acf6-34821adb9a1a",
 "documentTitle": "Offerte #20266956",
 "documentStatus": "DRAFT",
 "documentNumber": "20266956",
 "documentType": "QUOTATION",
 "title": "Offerte #20266956",
 "quotationNumber": "20266956",
 "quotationTitle": "Offerte #20266956",
 "quotationCreationTimestamp": 1781243829096,
 "quotationExpirationTimestamp": 1783835829096,
 "quotationStatus": "DRAFT",
 "isoCurrency": "EUR",
 "subjects": {
  "leadConfiguration": "68d41b06-d748-49e9-bd28-43eb3f6835f9",
  "contactPerson": "0a22a393-230b-494c-8340-bd8ea4e243b3"
 },
 "segments": {
  "defaultTemplateContactPart": {
   "type": "contactPerson",
   "data": "**${contactPerson.name}**\n${contactPerson.address}\n${contactPerson.email}\n${contactPerson.phoneNumber}"
  },
  "defaultSignaturePart": {
   "type": "signature",
   "data": {}
  },
  "defaultTemplateProfileLogo": {
   "type": "companyProfileLogo",
   "data": "![|6lh]($companyProfile.logo)"
  },
  "defaultTemplateProfileText": {
   "type": "text",
   "data": "[[right]]**${companyProfile.name}**\n${companyProfile.addressLine}\n${companyProfile.postalCode} ${companyProfile.city}"
  },
  "defaultTemplatePriceLineGroup": {
   "type": "priceLineGroup",
   "data": {
    "lines": [
     {
      "units": 1,
      "description": "Rolluik (RollSUPER)\nBreedte: 1480 mm\nHoogte: 1000 mm\nKastmaat: 170 mm (schuin)\nFrame Kleur: RAL 7016 structuur\nKleur Pantser: RAL 7016\nOnderlat: Standaard\nBediening: Draaischakelaar\nPaneel zijde: NTB\nLamel: RS 42, 1,0 cm dik.\nMontage: NTB\n\nGarantie:\n- 5 jaar op het product\n- 7 jaar op de motor",
      "pricePerUnit": 728.3,
      "vatPercentage": 21,
      "lockTotalPrice": false
     },
     {
      "units": 1,
      "description": "Inmeten + montage rolluik solar\n- Montage\n- Klein materiaal\n- Afstellen motor\n- Verwerken verpakkingsmateriaal",
      "pricePerUnit": 175,
      "vatPercentage": 21,
      "lockTotalPrice": false
     },
     {
      "units": 1,
      "description": "Rolluik (RollSUPER)\nBreedte: 2730 mm\nHoogte: 1370 mm\nKastmaat: 170 mm (schuin)\nFrame Kleur: RAL 7016 structuur\nKleur Pantser: RAL 7016\nOnderlat: Standaard\nBediening: Draaischakelaar\nPaneel zijde: NTB\nLamel: RS 42, 1,0 cm dik.\nMontage: NTB\n\nGarantie:\n- 5 jaar op het product\n- 7 jaar op de motor",
      "pricePerUnit": 1045.1,
      "vatPercentage": 21,
      "lockTotalPrice": false
     },
     {
      "units": 1,
      "description": "Inmeten + montage rolluik solar\n- Montage\n- Klein materiaal\n- Afstellen motor\n- Verwerken verpakkingsmateriaal",
      "pricePerUnit": 175,
      "vatPercentage": 21,
      "lockTotalPrice": false
     }
    ],
    "vatSetting": "INCL",
    "groupDiscount": {
     "name": "15% tijdelijke actie",
     "amount": 15,
     "type": "PERCENTAGE",
     "vatPercentage": 21
    }
   }
  }
 },
 "pricing": {
  "total": 1804.8899999999999
 },
 "renderRows": [
  {
   "delegateMargins": false,
   "widths": [
    50,
    50
   ],
   "columns": [
    {
     "elements": [
      {
       "type": "text",
       "target": "defaultTemplateProfileLogo"
      }
     ]
    },
    {
     "elements": [
      {
       "type": "text",
       "target": "defaultTemplateProfileText"
      }
     ]
    }
   ]
  },
  {
   "delegateMargins": false,
   "widths": [
    100
   ],
   "columns": [
    {
     "elements": [
      {
       "type": "empty"
      }
     ]
    }
   ]
  },
  {
   "delegateMargins": false,
   "widths": [
    100
   ],
   "columns": [
    {
     "elements": [
      {
       "type": "text",
       "target": "defaultTemplateContactPart"
      }
     ]
    }
   ]
  },
  {
   "delegateMargins": false,
   "widths": [
    100
   ],
   "columns": [
    {
     "elements": [
      {
       "type": "empty",
       "target": "2lh"
      }
     ]
    }
   ]
  },
  {
   "delegateMargins": false,
   "widths": [
    100
   ],
   "columns": [
    {
     "elements": [
      {
       "type": "quotationData"
      }
     ]
    }
   ]
  },
  {
   "delegateMargins": false,
   "widths": [
    100
   ],
   "columns": [
    {
     "elements": [
      {
       "type": "empty",
       "target": "2lh"
      }
     ]
    }
   ]
  },
  {
   "delegateMargins": false,
   "widths": [
    100
   ],
   "columns": [
    {
     "elements": [
      {
       "type": "priceLineGroupCombined",
       "target": "defaultTemplatePriceLineGroup"
      }
     ]
    }
   ]
  },
  {
   "delegateMargins": false,
   "widths": [
    100
   ],
   "columns": [
    {
     "elements": [
      {
       "type": "empty",
       "target": "2lh"
      }
     ]
    }
   ]
  },
  {
   "delegateMargins": false,
   "widths": [
    50,
    50
   ],
   "columns": [
    {
     "elements": [
      {
       "type": "userDecline"
      }
     ]
    },
    {
     "elements": [
      {
       "type": "signature",
       "target": "defaultSignaturePart"
      }
     ]
    }
   ]
  }
 ]
}