{
 "documentId": "8f20936d-1067-4104-8655-3516b36a7003",
 "versionId": "9000dd85-cf63-45d3-a1ff-d114a5d7a899",
 "documentTitle": "Offerte #20260244",
 "documentStatus": "SENT",
 "documentNumber": "20260244",
 "documentType": "QUOTATION",
 "title": "Offerte #20260244",
 "quotationNumber": "20260244",
 "quotationTitle": "Offerte #20260244",
 "quotationCreationTimestamp": 1768333366540,
 "quotationExpirationTimestamp": 1770925366540,
 "quotationStatus": "SENT",
 "isoCurrency": "EUR",
 "subjects": {
  "leadConfiguration": "c1a95dc7-b289-4206-b684-ae3bba999318",
  "contactPerson": "871d74a8-f434-4105-b435-ec6a8818eb32"
 },
 "segments": {
  "defaultTemplateContactPart": {
   "type": "contactPerson",
   "data": "**${contactPerson.name}**\n${contactPerson.address}\n${contactPerson.email}\n${contactPerson.phoneNumber}"
  },
  "defaultSignaturePart": {
   "type": "signature",
   "data": {}
  },
  "defaultTemplateProfileLogo": {
   "type": "companyProfileLogo",
   "data": "![|6lh]($companyProfile.logo)"
  },
  "defaultTemplateProfileText": {
   "type": "text",
   "data": "[[right]]**${companyProfile.name}**\n${companyProfile.addressLine}\n${companyProfile.postalCode} ${companyProfile.city}"
  },
  "defaultTemplatePriceLineGroup": {
   "type": "priceLineGroup",
   "data": {
    "lines": [
     {
      "units": 1,
      "description": "Pergola 165 zip\nBreedte: 11000 mm\nUitval: 4000 mm\nFrame Kleur: RAL 7016 structuur\nKleur doek: NTB\nBediening: Motor + afstandsbediening\nMotorzijde: NTB\nKleur/lengte motorkabel: NTB\nMontagesteunen: NTB\nOverige: NTB\n\nGarantie:\n- 5 jaar op het product.\n- 7 jaar op de motor",
      "pricePerUnit": 15392,
      "vatPercentage": 21,
      "lockTotalPrice": false
     },
     {
      "units": 1,
      "description": "Montage Pergola\n- Montage\n- Klein materiaal\n- Afstellen\n- Elektra afwerken",
      "pricePerUnit": 450,
      "vatPercentage": 21,
      "lockTotalPrice": false
     }
    ],
    "vatSetting": "INCL",
    "groupDiscount": {
     "name": "15% tijdelijke actie",
     "amount": 15,
     "type": "PERCENTAGE",
     "vatPercentage": 21
    }
   }
  }
 },
 "pricing": {
  "total": 13465.7
 },
 "renderRows": [
  {
   "delegateMargins": false,
   "widths": [
    50,
    50
   ],
   "columns": [
    {
     "elements": [
      {
       "type": "text",
       "target": "defaultTemplateProfileLogo"
      }
     ]
    },
    {
     "elements": [
      {
       "type": "text",
       "target": "defaultTemplateProfileText"
      }
     ]
    }
   ]
  },
  {
   "delegateMargins": false,
   "widths": [
    100
   ],
   "columns": [
    {
     "elements": [
      {
       "type": "empty"
      }
     ]
    }
   ]
  },
  {
   "delegateMargins": false,
   "widths": [
    100
   ],
   "columns": [
    {
     "elements": [
      {
       "type": "text",
       "target": "defaultTemplateContactPart"
      }
     ]
    }
   ]
  },
  {
   "delegateMargins": false,
   "widths": [
    100
   ],
   "columns": [
    {
     "elements": [
      {
       "type": "empty",
       "target": "2lh"
      }
     ]
    }
   ]
  },
  {
   "delegateMargins": false,
   "widths": [
    100
   ],
   "columns": [
    {
     "elements": [
      {
       "type": "quotationData"
      }
     ]
    }
   ]
  },
  {
   "delegateMargins": false,
   "widths": [
    100
   ],
   "columns": [
    {
     "elements": [
      {
       "type": "empty",
       "target": "2lh"
      }
     ]
    }
   ]
  },
  {
   "delegateMargins": false,
   "widths": [
    100
   ],
   "columns": [
    {
     "elements": [
      {
       "type": "priceLineGroupCombined",
       "target": "defaultTemplatePriceLineGroup"
      }
     ]
    }
   ]
  },
  {
   "delegateMargins": false,
   "widths": [
    100
   ],
   "columns": [
    {
     "elements": [
      {
       "type": "empty",
       "target": "2lh"
      }
     ]
    }
   ]
  },
  {
   "delegateMargins": false,
   "widths": [
    50,
    50
   ],
   "columns": [
    {
     "elements": [
      {
       "type": "userDecline"
      }
     ]
    },
    {
     "elements": [
      {
       "type": "signature",
       "target": "defaultSignaturePart"
      }
     ]
    }
   ]
  }
 ]
}