{
 "documentId": "6379ab21-ed98-4564-a6e4-b380c31e9a43",
 "versionId": "16fc7723-2b83-4375-9645-ad30ae45b25a",
 "documentTitle": "Offerte #20266561",
 "documentStatus": "SENT",
 "documentNumber": "20266561",
 "documentType": "QUOTATION",
 "title": "Offerte #20266561",
 "quotationNumber": "20266561",
 "quotationTitle": "Offerte #20266561",
 "quotationCreationTimestamp": 1780414303866,
 "quotationExpirationTimestamp": 1783006303866,
 "quotationStatus": "SENT",
 "isoCurrency": "EUR",
 "subjects": {
  "leadConfiguration": "9a0ab7d0-9efa-4f3e-9afa-df6ec48d501a",
  "contactPerson": "ff79914a-22e8-459f-86fa-478af09738b5"
 },
 "segments": {
  "defaultTemplateContactPart": {
   "type": "contactPerson",
   "data": "**${contactPerson.name}**\n${contactPerson.address}\n${contactPerson.email}\n${contactPerson.phoneNumber}"
  },
  "defaultSignaturePart": {
   "type": "signature",
   "data": {}
  },
  "defaultTemplateProfileLogo": {
   "type": "companyProfileLogo",
   "data": "![|6lh]($companyProfile.logo)"
  },
  "defaultTemplateProfileText": {
   "type": "text",
   "data": "[[right]]**${companyProfile.name}**\n${companyProfile.addressLine}\n${companyProfile.postalCode} ${companyProfile.city}"
  },
  "defaultTemplatePriceLineGroup": {
   "type": "priceLineGroup",
   "data": {
    "lines": [
     {
      "units": 1,
      "description": "SunBasic Cassette\nBreedte: 3000mm\nUitval: 2500 mm\nFrame Kleur: RAL 9001\nKleur doek: NTB\nBediening: Draaischakelaar\nMotorzijde: NTB\nKleur/lengte motorkabel: NTB\nOverige: NTB\n\nGarantie:\n- 5 jaar op het product.\n- 7 jaar op de motor",
      "pricePerUnit": 2376.7,
      "vatPercentage": 21,
      "lockTotalPrice": false
     },
     {
      "units": 1,
      "description": "montage Knikarmscherm.\n- Zonder uitbouw\n- Montage d.m.v. chemisch anker\n- Afwerken elektra\n- Klein materiaal\n- Afstellen zonwering\n- Verwerken verpakkingsmateriaal",
      "pricePerUnit": 275,
      "vatPercentage": 21,
      "lockTotalPrice": false
     }
    ],
    "vatSetting": "INCL",
    "groupDiscount": {
     "name": "15% tijdelijke actie",
     "amount": 15,
     "type": "PERCENTAGE",
     "vatPercentage": 21
    }
   }
  }
 },
 "pricing": {
  "total": 2253.9449999999997
 },
 "renderRows": [
  {
   "delegateMargins": false,
   "widths": [
    50,
    50
   ],
   "columns": [
    {
     "elements": [
      {
       "type": "text",
       "target": "defaultTemplateProfileLogo"
      }
     ]
    },
    {
     "elements": [
      {
       "type": "text",
       "target": "defaultTemplateProfileText"
      }
     ]
    }
   ]
  },
  {
   "delegateMargins": false,
   "widths": [
    100
   ],
   "columns": [
    {
     "elements": [
      {
       "type": "empty"
      }
     ]
    }
   ]
  },
  {
   "delegateMargins": false,
   "widths": [
    100
   ],
   "columns": [
    {
     "elements": [
      {
       "type": "text",
       "target": "defaultTemplateContactPart"
      }
     ]
    }
   ]
  },
  {
   "delegateMargins": false,
   "widths": [
    100
   ],
   "columns": [
    {
     "elements": [
      {
       "type": "empty",
       "target": "2lh"
      }
     ]
    }
   ]
  },
  {
   "delegateMargins": false,
   "widths": [
    100
   ],
   "columns": [
    {
     "elements": [
      {
       "type": "quotationData"
      }
     ]
    }
   ]
  },
  {
   "delegateMargins": false,
   "widths": [
    100
   ],
   "columns": [
    {
     "elements": [
      {
       "type": "empty",
       "target": "2lh"
      }
     ]
    }
   ]
  },
  {
   "delegateMargins": false,
   "widths": [
    100
   ],
   "columns": [
    {
     "elements": [
      {
       "type": "priceLineGroupCombined",
       "target": "defaultTemplatePriceLineGroup"
      }
     ]
    }
   ]
  },
  {
   "delegateMargins": false,
   "widths": [
    100
   ],
   "columns": [
    {
     "elements": [
      {
       "type": "empty",
       "target": "2lh"
      }
     ]
    }
   ]
  },
  {
   "delegateMargins": false,
   "widths": [
    50,
    50
   ],
   "columns": [
    {
     "elements": [
      {
       "type": "userDecline"
      }
     ]
    },
    {
     "elements": [
      {
       "type": "signature",
       "target": "defaultSignaturePart"
      }
     ]
    }
   ]
  }
 ]
}