{
 "documentId": "48a284c3-1f45-4cec-a792-49ccb70609be",
 "versionId": "8a047582-dd24-4036-a613-e3dda0b2e33b",
 "documentTitle": "Offerte #20267328",
 "documentStatus": "SENT",
 "documentNumber": "20267328",
 "documentType": "QUOTATION",
 "title": "Offerte #20267328",
 "quotationNumber": "20267328",
 "quotationTitle": "Offerte #20267328",
 "quotationCreationTimestamp": 1781930078147,
 "quotationExpirationTimestamp": 1784522078147,
 "quotationStatus": "SENT",
 "isoCurrency": "EUR",
 "subjects": {
  "leadConfiguration": "de54e2be-4004-4f03-8be0-9580efdbf982",
  "contactPerson": "411f98a9-007b-40ab-949f-73634b89dd52"
 },
 "segments": {
  "defaultTemplateContactPart": {
   "type": "contactPerson",
   "data": "**${contactPerson.name}**\n${contactPerson.address}\n${contactPerson.email}\n${contactPerson.phoneNumber}"
  },
  "e7fc90fa-311d-4b71-b6f9-07ab768e615a": {
   "type": "text",
   "data": "**Waarom Sonty?**\n\n- Sunmaster Premium Dealer: wij leveren uitsluitend A-merk zonwering van de hoogste kwaliteit\n- Eigen montageteam: al onze monteurs zijn in dienst, geen onderaannemers\n- Persoonlijk advies: gratis inmeetafspraak bij u thuis\n- 3000+ tevreden klanten\n- 4.9/5.0 op Google met 500+ reviews\n- Alles uit eigen hand: van advies tot montage en nazorg"
  },
  "defaultSignaturePart": {
   "type": "signature",
   "data": {}
  },
  "defaultTemplateProfileLogo": {
   "type": "companyProfileLogo",
   "data": "![|6lh]($companyProfile.logo)"
  },
  "defaultTemplateProfileText": {
   "type": "text",
   "data": "[[right]]**${companyProfile.name}**\n${companyProfile.addressLine}\n${companyProfile.postalCode} ${companyProfile.city}"
  },
  "defaultTemplatePriceLineGroup": {
   "type": "priceLineGroup",
   "data": {
    "lines": [
     {
      "units": 1,
      "description": "**Rolluik (RollSUPER)**\nType: rolluik draaischakelaar\nBreedte: 1000 mm\nHoogte: 2800 mm\nKastmaat: 170 mm (schuin)\nFrame Kleur: RAL 9010\nKleur Pantser: RAL 7016\nOnderlat: Standaard\nBediening: vaste draaischakelaar op de muur\nMotor: Somfy LT\nPaneel zijde: NTB\nLamel: RS 42, 1,0 cm dik.\nMontage: NTB\n\nWaarom dit rolluik:\n- Sunmaster RollSUPER: premium kwaliteit, Nederlands geproduceerd\n- Dubbelwandige aluminium lamellen met PU-schuim voor isolatie\n- Somfy motor met vaste draaischakelaar op de muur\n- Bescherming tegen inbraak, zon, warmte en kou\n\nGarantie:\n- 5 jaar op het product\n- 7 jaar op de motor",
      "pricePerUnit": 899.9,
      "vatPercentage": 21,
      "lockTotalPrice": false
     },
     {
      "units": 1,
      "description": "**Inmeten + montage rolluik**\n- Montage\n- Klein materiaal\n- Afstellen motor\n- Verwerken verpakkingsmateriaal",
      "pricePerUnit": 225,
      "vatPercentage": 21,
      "lockTotalPrice": false
     }
    ],
    "vatSetting": "INCL",
    "groupDiscount": {
     "name": "15% tijdelijke actie",
     "amount": 15,
     "type": "PERCENTAGE",
     "vatPercentage": 21
    }
   }
  }
 },
 "pricing": {
  "total": 956.1650000000001
 },
 "renderRows": [
  {
   "delegateMargins": false,
   "widths": [
    50,
    50
   ],
   "columns": [
    {
     "elements": [
      {
       "type": "text",
       "target": "defaultTemplateProfileLogo"
      }
     ]
    },
    {
     "elements": [
      {
       "type": "text",
       "target": "defaultTemplateProfileText"
      }
     ]
    }
   ]
  },
  {
   "delegateMargins": false,
   "widths": [
    100
   ],
   "columns": [
    {
     "elements": [
      {
       "type": "empty"
      }
     ]
    }
   ]
  },
  {
   "delegateMargins": false,
   "widths": [
    100
   ],
   "columns": [
    {
     "elements": [
      {
       "type": "text",
       "target": "defaultTemplateContactPart"
      }
     ]
    }
   ]
  },
  {
   "delegateMargins": false,
   "widths": [
    100
   ],
   "columns": [
    {
     "elements": [
      {
       "type": "empty",
       "target": "2lh"
      }
     ]
    }
   ]
  },
  {
   "delegateMargins": false,
   "widths": [
    100
   ],
   "columns": [
    {
     "elements": [
      {
       "type": "quotationData"
      }
     ]
    }
   ]
  },
  {
   "delegateMargins": false,
   "widths": [
    100
   ],
   "columns": [
    {
     "elements": [
      {
       "type": "empty",
       "target": "2lh"
      }
     ]
    }
   ]
  },
  {
   "delegateMargins": false,
   "widths": [
    100
   ],
   "columns": [
    {
     "elements": [
      {
       "type": "priceLineGroupCombined",
       "target": "defaultTemplatePriceLineGroup"
      }
     ]
    }
   ]
  },
  {
   "delegateMargins": false,
   "widths": [
    100
   ],
   "columns": [
    {
     "elements": [
      {
       "type": "empty",
       "target": "2lh"
      }
     ]
    }
   ]
  },
  {
   "delegateMargins": false,
   "widths": [
    100
   ],
   "columns": [
    {
     "elements": [
      {
       "type": "empty",
       "target": "2lh"
      }
     ]
    }
   ]
  },
  {
   "delegateMargins": false,
   "widths": [
    100
   ],
   "columns": [
    {
     "elements": [
      {
       "type": "text",
       "target": "e7fc90fa-311d-4b71-b6f9-07ab768e615a"
      }
     ]
    }
   ]
  },
  {
   "delegateMargins": false,
   "widths": [
    100
   ],
   "columns": [
    {
     "elements": [
      {
       "type": "empty",
       "target": "2lh"
      }
     ]
    }
   ]
  },
  {
   "delegateMargins": false,
   "widths": [
    50,
    50
   ],
   "columns": [
    {
     "elements": [
      {
       "type": "userDecline"
      }
     ]
    },
    {
     "elements": [
      {
       "type": "signature",
       "target": "defaultSignaturePart"
      }
     ]
    }
   ]
  }
 ]
}