{
 "documentId": "01dded1f-743a-4609-83a0-77a58d260e9f",
 "versionId": "09280b74-1517-4a52-8db9-6e37406e08d5",
 "documentTitle": "Offerte #20266931",
 "documentStatus": "DRAFT",
 "documentNumber": "20266931",
 "documentType": "QUOTATION",
 "title": "Offerte #20266931",
 "quotationNumber": "20266931",
 "quotationTitle": "Offerte #20266931",
 "quotationCreationTimestamp": 1781177851945,
 "quotationExpirationTimestamp": 1783769851945,
 "quotationStatus": "DRAFT",
 "isoCurrency": "EUR",
 "subjects": {
  "leadConfiguration": "426d3ef6-0b48-473b-beb5-4f9638107b93",
  "contactPerson": "3981e943-3129-4541-a529-d8de32b82810"
 },
 "segments": {
  "defaultTemplateContactPart": {
   "type": "contactPerson",
   "data": "**${contactPerson.name}**\n${contactPerson.address}\n${contactPerson.email}\n${contactPerson.phoneNumber}"
  },
  "defaultSignaturePart": {
   "type": "signature",
   "data": {}
  },
  "defaultTemplateProfileLogo": {
   "type": "companyProfileLogo",
   "data": "![|6lh]($companyProfile.logo)"
  },
  "defaultTemplateProfileText": {
   "type": "text",
   "data": "[[right]]**${companyProfile.name}**\n${companyProfile.addressLine}\n${companyProfile.postalCode} ${companyProfile.city}"
  },
  "defaultTemplatePriceLineGroup": {
   "type": "priceLineGroup",
   "data": {
    "lines": [
     {
      "units": 1,
      "description": "Rolluik (RollSUPER)\nBreedte: 1492 mm\nHoogte: 1620 mm\nKastmaat: 170 mm (schuin)\nFrame Kleur: RAL 7039\nKleur Pantser: RAL 7016\nOnderlat: Standaard\nBediening: Somfy IO motor solar\nPaneel zijde: NTB\nLamel: RS 42, 1,0 cm dik.\nMontage: NTB\n\nGarantie:\n- 5 jaar op het product\n- 7 jaar op de motor",
      "pricePerUnit": 1317.2,
      "vatPercentage": 21,
      "lockTotalPrice": false
     },
     {
      "units": 1,
      "description": "Inmeten + montage rolluik solar\n- Montage\n- Klein materiaal\n- Afstellen motor\n- Verwerken verpakkingsmateriaal",
      "pricePerUnit": 175,
      "vatPercentage": 21,
      "lockTotalPrice": false
     },
     {
      "units": 1,
      "description": "Tahoma Switch\n•⁠  ⁠Automatiseren van je Somfy producten.\n•⁠  ⁠⁠Producten bedienen waar je ook bent met de telefoon.\n•⁠  ⁠⁠Inclusief installatie en uitleg.\n•⁠  ⁠Al uw smart home producten op 1 app (zoals Phillips hue)",
      "pricePerUnit": 195,
      "vatPercentage": 21,
      "lockTotalPrice": false
     },
     {
      "units": 1,
      "description": "Rolluik (RollSUPER)\nBreedte: 2090 mm\nHoogte: 1620 mm\nKastmaat: 170 mm (schuin)\nFrame Kleur: RAL 7039\nKleur Pantser: RAL 7016\nOnderlat: Standaard\nBediening: Somfy IO motor solar\nPaneel zijde: NTB\nLamel: RS 42, 1,0 cm dik.\nMontage: NTB\n\nGarantie:\n- 5 jaar op het product\n- 7 jaar op de motor",
      "pricePerUnit": 1453.6,
      "vatPercentage": 21,
      "lockTotalPrice": false
     },
     {
      "units": 1,
      "description": "Inmeten + montage rolluik solar\n- Montage\n- Klein materiaal\n- Afstellen motor\n- Verwerken verpakkingsmateriaal",
      "pricePerUnit": 175,
      "vatPercentage": 21,
      "lockTotalPrice": false
     },
     {
      "units": 1,
      "description": "Tahoma Switch\n•⁠  ⁠Automatiseren van je Somfy producten.\n•⁠  ⁠⁠Producten bedienen waar je ook bent met de telefoon.\n•⁠  ⁠⁠Inclusief installatie en uitleg.\n•⁠  ⁠Al uw smart home producten op 1 app (zoals Phillips hue)",
      "pricePerUnit": 195,
      "vatPercentage": 21,
      "lockTotalPrice": false
     }
    ],
    "vatSetting": "INCL",
    "groupDiscount": {
     "name": "15% tijdelijke actie",
     "amount": 15,
     "type": "PERCENTAGE",
     "vatPercentage": 21
    }
   }
  }
 },
 "pricing": {
  "total": 2984.18
 },
 "renderRows": [
  {
   "delegateMargins": false,
   "widths": [
    50,
    50
   ],
   "columns": [
    {
     "elements": [
      {
       "type": "text",
       "target": "defaultTemplateProfileLogo"
      }
     ]
    },
    {
     "elements": [
      {
       "type": "text",
       "target": "defaultTemplateProfileText"
      }
     ]
    }
   ]
  },
  {
   "delegateMargins": false,
   "widths": [
    100
   ],
   "columns": [
    {
     "elements": [
      {
       "type": "empty"
      }
     ]
    }
   ]
  },
  {
   "delegateMargins": false,
   "widths": [
    100
   ],
   "columns": [
    {
     "elements": [
      {
       "type": "text",
       "target": "defaultTemplateContactPart"
      }
     ]
    }
   ]
  },
  {
   "delegateMargins": false,
   "widths": [
    100
   ],
   "columns": [
    {
     "elements": [
      {
       "type": "empty",
       "target": "2lh"
      }
     ]
    }
   ]
  },
  {
   "delegateMargins": false,
   "widths": [
    100
   ],
   "columns": [
    {
     "elements": [
      {
       "type": "quotationData"
      }
     ]
    }
   ]
  },
  {
   "delegateMargins": false,
   "widths": [
    100
   ],
   "columns": [
    {
     "elements": [
      {
       "type": "empty",
       "target": "2lh"
      }
     ]
    }
   ]
  },
  {
   "delegateMargins": false,
   "widths": [
    100
   ],
   "columns": [
    {
     "elements": [
      {
       "type": "priceLineGroupCombined",
       "target": "defaultTemplatePriceLineGroup"
      }
     ]
    }
   ]
  },
  {
   "delegateMargins": false,
   "widths": [
    100
   ],
   "columns": [
    {
     "elements": [
      {
       "type": "empty",
       "target": "2lh"
      }
     ]
    }
   ]
  },
  {
   "delegateMargins": false,
   "widths": [
    50,
    50
   ],
   "columns": [
    {
     "elements": [
      {
       "type": "userDecline"
      }
     ]
    },
    {
     "elements": [
      {
       "type": "signature",
       "target": "defaultSignaturePart"
      }
     ]
    }
   ]
  }
 ]
}